{
    "height": 0,
    "width": 0,
    "depth": 0,
    "displayedHeight": 0,
    "displayedWidth": 0,
    "displayedDepth": 0,
    "perspectiveImage": "https://catalog.roomle.com/c40fc0f3-047e-4976-8c3a-aba71edc1394/items/interior_set_1/perspectiveImage.png?marker=1729721311",
    "perspectiveImageHD": "https://catalog.roomle.com/c40fc0f3-047e-4976-8c3a-aba71edc1394/items/interior_set_1/perspectiveImageHD.png?marker=1729721311",
    "topImage": "https://catalog.roomle.com/c40fc0f3-047e-4976-8c3a-aba71edc1394/items/interior_set_1/topImage.png?marker=1729721311",
    "assets": {},
    "externalIdentifier": "interior_set_1",
    "configuration": "{\"componentId\":\"betzold_flexeo:flexeo_interior_set\"}",
    "rootComponentId": "betzold_flexeo:flexeo_interior_set",
    "hidden": false,
    "visibilityStatus": 0,
    "created": "2024-10-16T09:05:49.000Z",
    "updated": "2024-10-23T22:08:31.000Z",
    "flipable": false,
    "scaleable": false,
    "colorable": false,
    "basecolor": "0",
    "orderable": false,
    "requestable": false,
    "retailPriceAllowed": false,
    "label": "Set 1",
    "language": "en",
    "catalog": "betzold_flexeo",
    "id": "betzold_flexeo:interior_set_1",
    "tags": [
        "betzold_sets"
    ],
    "links": {
        "tags": "/items/betzold_flexeo:interior_set_1/tags",
        "similarItems": "/items/betzold_flexeo:interior_set_1/similarItems",
        "perfectFit": "/items/betzold_flexeo:interior_set_1/perfectFit",
        "additionalContents": "/items/betzold_flexeo:interior_set_1/additionalContents"
    },
    "attributes": [],
    "version": 3
}